isuvalidation/__init__.py
isuvalidation/config.py
isuvalidation/login.py
isuvalidation/utils.py
isuvalidation-0.1.1.dist-info/METADATA
isuvalidation-0.1.1.dist-info/WHEEL
isuvalidation-0.1.1.dist-info/top_level.txt
isuvalidation-0.1.1.dist-info/RECORD
