Metadata-Version: 2.4
Name: isuvalidation
Version: 0.1.1
Summary: Credential validation helper for any project.
Author: yannickRafael
Requires-Python: >=3.9
Requires-Dist: requests>=2.31
Requires-Dist: python-dotenv>=1.0
